ComunioScore/__init__.py
ComunioScore/api.py
ComunioScore/app.py
ComunioScore/comunio.py
ComunioScore/comuniodb.py
ComunioScore/dbhandler.py
ComunioScore/exceptions.py
ComunioScore/livedata.py
ComunioScore/matchscheduler.py
ComunioScore/pointcalculator.py
ComunioScore/scheduler.py
ComunioScore/sofascoredb.py
ComunioScore/config/comunioscore.ini
ComunioScore/db/__init__.py
ComunioScore/db/connector.py
ComunioScore/db/context.py
ComunioScore/db/creator.py
ComunioScore/db/fetcher.py
ComunioScore/db/inserter.py
ComunioScore/db/sqlite.py
ComunioScore/messenger/__init__.py
ComunioScore/messenger/comunioscore_telegram.py
ComunioScore/routes/__init__.py
ComunioScore/routes/router.py
ComunioScore/score/__init__.py
ComunioScore/score/bundesligascore.py
ComunioScore/score/sofascore.py
ComunioScore/test/__init__.py
ComunioScore/test/test_api.py
ComunioScore/test/test_comunio.py
ComunioScore/test/test_pointcalculator.py
ComunioScore/test/db/__init__.py
ComunioScore/test/db/test_connector.py
ComunioScore/test/db/test_creator.py
ComunioScore/test/db/test_fetcher.py
ComunioScore/test/db/test_inserter.py
ComunioScore/test/messenger/__init__.py
ComunioScore/test/messenger/test_comunioscore_telegram.py
ComunioScore/test/score/__init__.py
ComunioScore/test/score/test_bundesligascore.py
ComunioScore/test/score/test_sofascore.py
ComunioScore/utils/__init__.py
ComunioScore/utils/logger.py
ComunioScore-1.0.9.dist-info/LICENSE
ComunioScore-1.0.9.dist-info/METADATA
ComunioScore-1.0.9.dist-info/WHEEL
ComunioScore-1.0.9.dist-info/entry_points.txt
ComunioScore-1.0.9.dist-info/top_level.txt
ComunioScore-1.0.9.dist-info/RECORD
